example/__init__.py
example/kmeans.py
example/perceptron.py
slmethod/__init__.py
slmethod/kmeans.py
slmethod/perceptron.py
slmethod/base/__init__.py
slmethod/base/base.py
slmethod/test/__init__.py
slmethod/test/test_kmeans.py
slmethod/test/test_perceptron.py
slmethod/utils/__init__.py
slmethod/utils/_show_versions.py
slmethod-0.2.6.dist-info/LICENSE
slmethod-0.2.6.dist-info/METADATA
slmethod-0.2.6.dist-info/WHEEL
slmethod-0.2.6.dist-info/top_level.txt
slmethod-0.2.6.dist-info/RECORD
