Metadata-Version: 2.1
Name: slmethod
Version: 0.2.6
Summary: Statistical Learning Method package
Home-page: https://github.com/iOSDevLog/slmethod
Author: Xianhua Jia
Author-email: iosdevlog@iosdevlog.com
License: MIT
Platform: UNKNOWN
Classifier: Programming Language :: Python :: 3
Classifier: Programming Language :: Python :: 3.5
Classifier: Programming Language :: Python :: 3.6
Classifier: Programming Language :: Python :: 3.7
Classifier: License :: OSI Approved :: MIT License
Classifier: Operating System :: Microsoft :: Windows
Classifier: Operating System :: POSIX
Classifier: Operating System :: Unix
Classifier: Operating System :: MacOS
Requires-Dist: tqdm (>=4.32)
Requires-Dist: numpy (>=1.16)
Requires-Dist: scipy (>=1.3)
Requires-Dist: matplotlib (>=3.0)
Requires-Dist: seaborn (>=0.9)
Requires-Dist: autograd (>=1.2)
Requires-Dist: joblib (>=0.13)
Requires-Dist: scikit-learn (>=0.21)
